AlgorithmImports/__init__.pyi
Calculators/__init__.py
Calculators/__init__.pyi
Calculators/DataType/__init__.py
Calculators/DataType/__init__.pyi
Calculators/Estimators/__init__.py
Calculators/Estimators/__init__.pyi
Calculators/IO/__init__.py
Calculators/IO/__init__.pyi
Calculators/Margins/__init__.py
Calculators/Margins/__init__.pyi
FtxApi/__init__.py
FtxApi/__init__.pyi
FtxApi/Rest/__init__.py
FtxApi/Rest/__init__.pyi
FtxApi/Rest/Enums/__init__.py
FtxApi/Rest/Enums/__init__.pyi
FtxApi/Rest/Models/__init__.py
FtxApi/Rest/Models/__init__.pyi
FtxApi/Rest/Models/LeveragedTokens/__init__.py
FtxApi/Rest/Models/LeveragedTokens/__init__.pyi
FtxApi/Rest/Models/Markets/__init__.py
FtxApi/Rest/Models/Markets/__init__.pyi
FtxApi/WebSocket/__init__.py
FtxApi/WebSocket/__init__.pyi
FtxApi/WebSocket/Models/__init__.py
FtxApi/WebSocket/Models/__init__.pyi
FtxApi/WsEngine/__init__.py
FtxApi/WsEngine/__init__.pyi
Internal/__init__.py
Internal/__init__.pyi
Internal/Runtime/__init__.py
Internal/Runtime/InteropServices/__init__.py
Internal/Runtime/InteropServices/__init__.pyi
Internal/Win32/__init__.py
Internal/Win32/SafeHandles/__init__.py
MS/__init__.py
MS/Internal/__init__.py
MS/Internal/Xml/__init__.py
MS/Internal/Xml/Linq/__init__.py
MS/Internal/Xml/Linq/ComponentModel/__init__.py
Microsoft/__init__.py
Microsoft/Win32/__init__.py
Microsoft/Win32/SafeHandles/__init__.py
Microsoft/Win32/SafeHandles/__init__.pyi
MomCrypto/__init__.py
MomCrypto/Api/__init__.py
MomCrypto/Api/__init__.pyi
MomCrypto/Api/Algorithm/__init__.py
MomCrypto/Api/Algorithm/__init__.pyi
MomCrypto/DataApi/__init__.py
MomCrypto/DataApi/__init__.pyi
MomCrypto/Frontend/__init__.py
MomCrypto/Frontend/__init__.pyi
QuantConnect/__init__.py
QuantConnect/__init__.pyi
QuantConnect/ABL/__init__.py
QuantConnect/ABL/__init__.pyi
QuantConnect/Algorithm/__init__.py
QuantConnect/Algorithm/__init__.pyi
QuantConnect/Algorithm/CSharp/__init__.py
QuantConnect/Algorithm/CSharp/__init__.pyi
abl_quantconnect_stubs-13987.7.dist-info/METADATA
abl_quantconnect_stubs-13987.7.dist-info/WHEEL
abl_quantconnect_stubs-13987.7.dist-info/top_level.txt
abl_quantconnect_stubs-13987.7.dist-info/RECORD
