Metadata-Version: 2.1
Name: abl-quantconnect-stubs
Version: 13987.7
Summary: Type stubs for QuantConnect's Lean
Home-page: https://github.com/QuantConnect/quantconnect-stubs-generator
Author: QuantConnect
Author-email: support@quantconnect.com
Classifier: Development Status :: 5 - Production/Stable
Classifier: Intended Audience :: Developers
Classifier: Intended Audience :: Financial and Insurance Industry
Classifier: License :: OSI Approved :: Apache Software License
Classifier: Programming Language :: Python :: 3
Requires-Dist: pandas (>=0.25.3)
Requires-Dist: matplotlib (>=3.2.1)
